README.md
setup.cfg
setup.py
tcp_connectors/__init__.py
tcp_connectors/exceptions.py
tcp_connectors/gmqtt_connector.py
tcp_connectors/server_connector.py
tcp_connectors/tcp_connector.py
tcp_connectors.egg-info/PKG-INFO
tcp_connectors.egg-info/SOURCES.txt
tcp_connectors.egg-info/dependency_links.txt
tcp_connectors.egg-info/requires.txt
tcp_connectors.egg-info/top_level.txt
tcp_connectors/base/__init__.py
tcp_connectors/base/base_connector.py