Metadata-Version: 2.1
Name: tcp-connectors
Version: 0.1.5
Summary: Connectors for connecting to any TCP-based service
Home-page: https://github.com/evocount/tcp-connectors
Author: EvoCount GmbH
Author-email: abhishek.mv1995@gmail.com
License: MIT
Download-URL: https://github.com/evocount/tcp-connectors/archive/v0.1.5.tar.gz
Platform: UNKNOWN
Classifier: Development Status :: 4 - Beta
Classifier: Intended Audience :: Developers
Classifier: Intended Audience :: System Administrators
Classifier: License :: OSI Approved :: MIT License
Classifier: Programming Language :: Python :: 3
Classifier: Programming Language :: Python :: 3.6
Requires-Python: >=3.6
